haproxyspoa/__init__.py
haproxyspoa/logging.py
haproxyspoa/spoa_data_types.py
haproxyspoa/spoa_frame.py
haproxyspoa/spoa_payloads.py
haproxyspoa/spoa_server.py
haproxyspoa/payloads/__init__.py
haproxyspoa/payloads/ack.py
haproxyspoa/payloads/agent_disconnect.py
haproxyspoa/payloads/agent_hello.py
haproxyspoa/payloads/haproxy_disconnect.py
haproxyspoa/payloads/haproxy_hello.py
haproxyspoa/payloads/notify.py
haproxyspoa-0.0.1.dist-info/LICENSE
haproxyspoa-0.0.1.dist-info/METADATA
haproxyspoa-0.0.1.dist-info/WHEEL
haproxyspoa-0.0.1.dist-info/top_level.txt
haproxyspoa-0.0.1.dist-info/RECORD
