Metadata-Version: 2.1
Name: haproxyspoa
Version: 0.0.1
Summary: A pure-python asyncio implementation of an HAProxy Stream Processing Offload Agent (SPOA)
Home-page: https://github.com/krrg/haproxy-python-spoa
Author: Ken Reese
Author-email: krrgithub@gmail.com
License: Apache 2
Platform: UNKNOWN
Classifier: License :: OSI Approved :: Apache Software License
Classifier: Programming Language :: Python :: 3
Classifier: Programming Language :: Python :: 3.7
Classifier: Programming Language :: Python :: 3.8
Classifier: Programming Language :: Python :: 3.9
Classifier: Development Status :: 2 - Pre-Alpha
Classifier: Topic :: System :: Networking
Classifier: Topic :: Internet :: WWW/HTTP
Classifier: Framework :: AsyncIO
